UCWrapBetterConfig/__init__.py
UCWrapBetterConfig/uc_wrap_better_config.py
UtilityCloudAPIWrapper/__init__.py
UtilityCloudAPIWrapper/_version.py
UtilityCloudAPIWrapper/initializer.py
UtilityCloudAPIWrapper/utility_cloud_api_wrapper.py
UtilityCloudAPIWrapper/Backend/__init__.py
UtilityCloudAPIWrapper/Backend/attribute_preprocess.py
UtilityCloudAPIWrapper/Backend/easy_requests.py
UtilityCloudAPIWrapper/Backend/enum.py
UtilityCloudAPIWrapper/Backend/err.py
UtilityCloudAPIWrapper/Backend/utility_cloud_auth.py
UtilityCloudAPIWrapper/Searchers/__init__.py
UtilityCloudAPIWrapper/Searchers/factory.py
UtilityCloudAPIWrapper/Searchers/return_search_objects.py
UtilityCloudAPIWrapper/Searchers/searchers.py
utilitycloudapiwrapper-1.2.1.dist-info/licenses/LICENSE.txt
utilitycloudapiwrapper-1.2.1.dist-info/METADATA
utilitycloudapiwrapper-1.2.1.dist-info/WHEEL
utilitycloudapiwrapper-1.2.1.dist-info/top_level.txt
utilitycloudapiwrapper-1.2.1.dist-info/RECORD
