Metadata-Version: 2.4
Name: UtilityCloudAPIWrapper
Version: 1.2.1
Summary: Python wrapper for the utility cloud API
Home-page: https://github.com/amcsparron2793-Water/UtilityCloudAPIWrapper
Download-URL: https://github.com/amcsparron2793-Water/UtilityCloudAPIWrapper/archive/refs/tags/1.2.1.tar.gz
Author: Amcsparron
Author-email: amcsparron@albanyny.gov
License: MIT License
License-File: LICENSE.txt
Requires-Dist: BetterConfigAJM
Requires-Dist: PurgeSecrets
Requires-Dist: requests
Requires-Dist: EasyLoggerAJM
Requires-Dist: tqdm
Dynamic: author
Dynamic: author-email
Dynamic: download-url
Dynamic: home-page
Dynamic: license
Dynamic: license-file
Dynamic: requires-dist
Dynamic: summary
